botglue/__init__.py
botglue/llit.py
botglue/misc.py
botglue/periodic.py
botglue/py.typed
botglue/service.py
botglue/llit_app/main.py
botglue/llore/__init__.py
botglue/llore/api.py
botglue/llore/chat.py
botglue/llore/config.py
botglue/llore/llm.py
botglue/llore/pipeline.py
botglue/llore/server.py
botglue/llore/utils.py
botglue/llore/vector.py
botglue/llore/state/__init__.py
botglue/llore/state/schema.py
botglue-0.0.6.dist-info/METADATA
botglue-0.0.6.dist-info/WHEEL
botglue-0.0.6.dist-info/entry_points.txt
botglue-0.0.6.dist-info/licenses/LICENSE
botglue-0.0.6.dist-info/RECORD
