Metadata-Version: 2.4
Name: botglue
Version: 0.0.6
Summary: botglue - Attempt to make Second Brain - Simple stand alone UI for RAG loader pipline/chatbot/api
Project-URL: Repository, https://github.com/walnutgeek/botglue
Author-email: Walnut Geek <wg@walnutgeek.com>
License-Expression: MIT
License-File: LICENSE
Classifier: Development Status :: 4 - Beta
Classifier: Intended Audience :: Developers
Classifier: Operating System :: OS Independent
Classifier: Programming Language :: Python
Classifier: Programming Language :: Python :: 3
Classifier: Programming Language :: Python :: 3.11
Classifier: Programming Language :: Python :: 3.12
Classifier: Programming Language :: Python :: 3.13
Classifier: Typing :: Typed
Requires-Python: <4.0,>=3.11
Requires-Dist: chromadb
Requires-Dist: langchain
Requires-Dist: langchain-chroma
Requires-Dist: langchain-community
Requires-Dist: langchain-huggingface
Requires-Dist: langchain-openai
Requires-Dist: numpy==2.1.0
Requires-Dist: pdf2image
Requires-Dist: pydantic
Requires-Dist: pypandoc
Requires-Dist: pytesseract
Requires-Dist: python-magic
Requires-Dist: scipy==1.14.1
Requires-Dist: sentence-transformers
Requires-Dist: streamlit-chat
Requires-Dist: streamlit>=1.32.0
Requires-Dist: transformers
Requires-Dist: typing-extensions
Requires-Dist: unstructured
